app/__init__.py
app/app.py
eyewear_counter/__init__.py
eyewear_counter/async_image_processor.py
eyewear_counter/classifier.py
eyewear_counter/detector.py
eyewear_counter/eyewear_counter.py
eyewear_counter/postprocess.py
eyewear_counter/utils.py
eyewear_counter-0.1.4.dist-info/licenses/LICENSE
eyewear_counter-0.1.4.dist-info/METADATA
eyewear_counter-0.1.4.dist-info/WHEEL
eyewear_counter-0.1.4.dist-info/entry_points.txt
eyewear_counter-0.1.4.dist-info/top_level.txt
eyewear_counter-0.1.4.dist-info/RECORD
