Metadata-Version: 2.4
Name: eyewear_counter
Version: 0.1.4
Summary: Fast model for counting eyewear types on faces in large sets of images.
Home-page: https://github.com/qksolov/eyewear-counter
Author: Ekaterina Solovyeva
Author-email: qksolov@gmail.com
License: MIT
Classifier: Programming Language :: Python :: 3
Classifier: License :: OSI Approved :: MIT License
Classifier: Operating System :: OS Independent
Requires-Python: >=3.8
License-File: LICENSE
Requires-Dist: torch
Requires-Dist: torchvision
Requires-Dist: ultralytics
Requires-Dist: opencv-python
Requires-Dist: numpy
Requires-Dist: pandas
Requires-Dist: aiohttp
Requires-Dist: tqdm
Requires-Dist: xlsxwriter
Requires-Dist: nest_asyncio
Requires-Dist: requests
Requires-Dist: gradio
Dynamic: author
Dynamic: author-email
Dynamic: classifier
Dynamic: description
Dynamic: description-content-type
Dynamic: home-page
Dynamic: license
Dynamic: license-file
Dynamic: requires-dist
Dynamic: requires-python
Dynamic: summary
